[
{
    "model": "administration.dummyitem",
    "pk": "138936a8-4818-4196-8f0a-9dbd019317cf",
    "fields": {
        "deleted": null,
        "deleted_by_cascade": false,
        "created_at": "2011-03-23T12:29:00Z",
        "updated_at": "2021-03-05T09:45:38Z",
        "description": "Tax able past large. Wait hold phone suggest red raise but. Phone up everybody theory product recently.\nMaybe paper would music message process. Simply away television clearly ever body."
    }
},
{
    "model": "administration.dummyitem",
    "pk": "5b1f463c-93bc-43b6-a639-cbfbbc48308e",
    "fields": {
        "deleted": null,
        "deleted_by_cascade": false,
        "created_at": "1974-07-17T18:34:25Z",
        "updated_at": "2013-07-12T02:03:22Z",
        "description": "Whom yeah individual career remain. Wrong feel hold same single different visit. Painting become culture surface might."
    }
},
{
    "model": "administration.dummyitem",
    "pk": "731d9f01-fd96-464f-8874-297ebb48742f",
    "fields": {
        "deleted": null,
        "deleted_by_cascade": false,
        "created_at": "2022-11-07T06:55:07Z",
        "updated_at": "1997-03-25T02:27:58Z",
        "description": "Hope structure far religious certain contain. Leader teacher fly technology time quite.\nReveal nothing product move often."
    }
},
{
    "model": "administration.dummyitem",
    "pk": "a5243109-5f40-4abd-859f-f40ae1740bc6",
    "fields": {
        "deleted": null,
        "deleted_by_cascade": false,
        "created_at": "2021-12-18T03:15:42Z",
        "updated_at": "2004-12-14T20:50:08Z",
        "description": "Cup bed easy address police old learn. Kind to human. Type detail career collection.\nOrganization red wrong. Act drive south treat. Serious short yard structure that easy health."
    }
},
{
    "model": "administration.dummyitem",
    "pk": "aff78a2c-6506-4b3a-8f7a-4b903340b25c",
    "fields": {
        "deleted": null,
        "deleted_by_cascade": false,
        "created_at": "2013-12-03T12:24:04Z",
        "updated_at": "1997-06-23T23:44:56Z",
        "description": "Yet hair forward now stock. Outside its pretty form federal from. Arrive hospital party factor expert likely."
    }
},
{
    "model": "administration.dummyitem",
    "pk": "b75cded0-9725-41b8-8f93-0d5a6b92b3ff",
    "fields": {
        "deleted": null,
        "deleted_by_cascade": false,
        "created_at": "1983-04-02T16:59:45Z",
        "updated_at": "1980-07-13T11:52:48Z",
        "description": "Service clear remain much center leave. Identify between reduce light budget. Others edge tend not live along."
    }
},
{
    "model": "administration.dummyitem",
    "pk": "be08a1ec-54f2-415d-80c8-d1925dde91b8",
    "fields": {
        "deleted": null,
        "deleted_by_cascade": false,
        "created_at": "1999-07-20T23:07:43Z",
        "updated_at": "2002-11-07T17:35:03Z",
        "description": "Girl former identify specific. A water Mr offer decade.\nBring still firm value raise explain. Everyone teach difficult somebody. Seek land strong as."
    }
},
{
    "model": "administration.dummyitem",
    "pk": "c24bcfea-d5b7-4cb6-adc9-1674609a8669",
    "fields": {
        "deleted": null,
        "deleted_by_cascade": false,
        "created_at": "2007-07-29T05:40:20Z",
        "updated_at": "2009-07-13T00:29:42Z",
        "description": "Woman represent fire establish white well since.\nKind spring away light get middle. Commercial sort hard reduce movement.\nSecurity model effect. Try nothing short tell."
    }
},
{
    "model": "administration.dummyitem",
    "pk": "e3cfb3a5-3a85-467d-9dc5-99984e111c85",
    "fields": {
        "deleted": null,
        "deleted_by_cascade": false,
        "created_at": "2008-10-21T01:49:06Z",
        "updated_at": "1989-06-01T11:49:10Z",
        "description": "Article paper stock tonight maintain. Out face for success. Rule education western. Total without year item low."
    }
},
{
    "model": "administration.dummyitem",
    "pk": "fe9f76a2-b1df-4533-8959-027d8c9e4ccf",
    "fields": {
        "deleted": null,
        "deleted_by_cascade": false,
        "created_at": "2022-04-02T15:41:08Z",
        "updated_at": "1989-10-02T08:25:39Z",
        "description": "Smile great around thank energy dog. Everything thank understand official step.\nAffect foreign during think. Stage race ask thus heavy position."
    }
}
]
